susie/__init__.py
susie/campaign.py
susie/ephemeris.py
susie/timing_data.py
susie-1.2.8.dist-info/licenses/LICENSE.txt
susie-1.2.8.dist-info/METADATA
susie-1.2.8.dist-info/WHEEL
susie-1.2.8.dist-info/top_level.txt
susie-1.2.8.dist-info/RECORD
