Metadata-Version: 2.4
Name: susie
Version: 1.2.8
Summary: Susie is a Python package for modeling the orbital evolution of exoplanets using transit and occultation timing data. It helps detect and characterize tidal orbital decay and apsidal precession, offering statistical tools to compare models and infer the physical processes shaping close-in planetary systems—linking timing data to insights on tidal dissipation, planetary interiors, and dynamical interactions.
Author: Malia Barker, Holly VanLooy, Adrienne Kirk
Author-email: maliabarker@icloud.com, hollyvanlooy@u.boisestate.edu, adriennekirk@u.boisestate.edu
Project-URL: Bug Tracker, https://github.com/BoiseStatePlanetary/susie/issues
Project-URL: Repository, https://github.com/BoiseStatePlanetary/susie/
Project-URL: Documentation, https://susie.readthedocs.io/en/latest/index.html
Classifier: Programming Language :: Python :: 3
Classifier: License :: OSI Approved :: MIT License
Classifier: Operating System :: OS Independent
Requires-Python: >=3.6
License-File: LICENSE.txt
Requires-Dist: pytz
Requires-Dist: pandas
Requires-Dist: numpy
Requires-Dist: lmfit
Requires-Dist: matplotlib
Requires-Dist: astropy
Requires-Dist: astroquery
Requires-Dist: astroplan
Dynamic: license-file
